pycosie/__init__.py
pycosie/cluster/__init__.py
pycosie/cluster/galfinder.py
pycosie/cluster/rockstar.py
pycosie/fileio/__init__.py
pycosie/fileio/reader.py
pycosie/utils/__init__.py
pycosie/utils/hostgal.py
pycosie/utils/powerspec.py
pycosie-0.2.1.dist-info/LICENSE
pycosie-0.2.1.dist-info/METADATA
pycosie-0.2.1.dist-info/WHEEL
pycosie-0.2.1.dist-info/top_level.txt
pycosie-0.2.1.dist-info/RECORD
