Metadata-Version: 2.1
Name: pycosie
Version: 0.2.1
Summary: Anaylsis tools to help with TD (and hopefully other simulations...)
Author: Samir Kusmic
License: GNU General Public License v2 (GPLv2)
Classifier: Programming Language :: Python :: 3
Classifier: License :: OSI Approved :: GNU General Public License v2 (GPLv2)
Classifier: Operating System :: OS Independent
License-File: LICENSE
Requires-Dist: numpy
Requires-Dist: scipy
Requires-Dist: yt
Requires-Dist: caesar
Requires-Dist: astropy
Requires-Dist: h5py
